xmpp_http_upload/__init__.py
xmpp_http_upload/admin.py
xmpp_http_upload/apps.py
xmpp_http_upload/models.py
xmpp_http_upload/querysets.py
xmpp_http_upload/tasks.py
xmpp_http_upload/tests.py
xmpp_http_upload/urls.py
xmpp_http_upload/utils.py
xmpp_http_upload/views.py
xmpp_http_upload/management/__init__.py
xmpp_http_upload/management/commands/__init__.py
xmpp_http_upload/management/commands/cleanup_http_uploads.py
xmpp_http_upload/migrations/0001_initial.py
xmpp_http_upload/migrations/0002_auto_20150913_1031.py
xmpp_http_upload/migrations/0003_auto_20161026_1220.py
xmpp_http_upload/migrations/0004_auto_20170309_2201.py
xmpp_http_upload/migrations/__init__.py
django_xmpp_http_upload-1.0.0.dist-info/LICENSE
django_xmpp_http_upload-1.0.0.dist-info/METADATA
django_xmpp_http_upload-1.0.0.dist-info/WHEEL
django_xmpp_http_upload-1.0.0.dist-info/top_level.txt
django_xmpp_http_upload-1.0.0.dist-info/RECORD
