Metadata-Version: 2.1
Name: django-xmpp-http-upload
Version: 1.0.0
Summary: Provides XEP-0363: HTTP File Upload
Home-page: https://github.com/mathiasertl/django-xmpp-http-upload
Author: Mathias Ertl
Author-email: mati@jabber.at
License: GNU General Public License (GPL) v3
Platform: UNKNOWN
Classifier: Development Status :: 4 - Beta
Classifier: Environment :: Web Environment
Classifier: Framework :: Django
Classifier: Intended Audience :: System Administrators
Classifier: License :: OSI Approved :: GNU General Public License v3 or later (GPLv3+)
Classifier: Operating System :: OS Independent
Classifier: Programming Language :: Python
Classifier: Programming Language :: Python :: 3
Classifier: Programming Language :: Python :: 3.5
Classifier: Programming Language :: Python :: 3.6
Classifier: Programming Language :: Python :: 3.7
Classifier: Programming Language :: Python :: 3.8
Classifier: Topic :: Internet :: WWW/HTTP
Classifier: Topic :: Communications :: File Sharing
Requires-Dist: Django (>=2.2)
Requires-Dist: djangorestframework (>=3.9)
